knn_kv/__init__.py
knn_kv-0.0.1.dist-info/LICENSE
knn_kv-0.0.1.dist-info/METADATA
knn_kv-0.0.1.dist-info/WHEEL
knn_kv-0.0.1.dist-info/top_level.txt
knn_kv-0.0.1.dist-info/RECORD
