Metadata-Version: 2.1
Name: knn-kv
Version: 0.0.1
Summary: k-nearest neighbors
Home-page: https://github.com/kopylovvlad/knn_kv
Author: Vladislav Kopylov
Author-email: kopylov.vlad@gmail.com
License: UNKNOWN
Platform: UNKNOWN
Requires-Python: >=3.5
